<annotation verified="no">
  <folder>image</folder>
  <filename>0364</filename>
  <path>/home/cd/huawei-ssd/hwdata/image/0364.jpg</path>
  <source>
    <database>Unknown</database>
  </source>
  <size>
    <width>2048</width>
    <height>2048</height>
    <depth>1</depth>
  </size>
  <segmented>0</segmented>
  <object>
    <name>guangkou</name>
    <pose>Unspecified</pose>
    <truncated>0</truncated>
    <difficult>0</difficult>
    <pbndbox>
      <ltopx>1128</ltopx>
      <ltopy>646</ltopy>
      <lbottomx>1138</lbottomx>
      <lbottomy>298</lbottomy>
      <rbottomx>920</rbottomx>
      <rbottomy>298</rbottomy>
      <rtopx>912</rtopx>
      <rtopy>644</rtopy>
    </pbndbox>
  </object>
  <object>
    <name>guangkou</name>
    <pose>Unspecified</pose>
    <truncated>0</truncated>
    <difficult>0</difficult>
    <pbndbox>
      <ltopx>1042</ltopx>
      <ltopy>1102</ltopy>
      <lbottomx>1044</lbottomx>
      <lbottomy>804</lbottomy>
      <rbottomx>854</rbottomx>
      <rbottomy>798</rbottomy>
      <rtopx>844</rtopx>
      <rtopy>1100</rtopy>
    </pbndbox>
  </object>
</annotation>
