<annotation verified="no">
  <folder>image</folder>
  <filename>1182</filename>
  <path>/home/cd/huawei-ssd/hwdata/image/1182.jpg</path>
  <source>
    <database>Unknown</database>
  </source>
  <size>
    <width>600</width>
    <height>600</height>
    <depth>1</depth>
  </size>
  <segmented>0</segmented>
  <object>
    <name>guangkou</name>
    <pose>Unspecified</pose>
    <truncated>0</truncated>
    <difficult>0</difficult>
    <pbndbox>
      <ltopx>455</ltopx>
      <ltopy>279</ltopy>
      <lbottomx>413</lbottomx>
      <lbottomy>298</lbottomy>
      <rbottomx>427</rbottomx>
      <rbottomy>327</rbottomy>
      <rtopx>466</rtopx>
      <rtopy>307</rtopy>
    </pbndbox>
  </object>
  <object>
    <name>guangkou</name>
    <pose>Unspecified</pose>
    <truncated>0</truncated>
    <difficult>0</difficult>
    <pbndbox>
      <ltopx>555</ltopx>
      <ltopy>230</ltopy>
      <lbottomx>513</lbottomx>
      <lbottomy>249</lbottomy>
      <rbottomx>524</rbottomx>
      <rbottomy>277</rbottomy>
      <rtopx>567</rtopx>
      <rtopy>259</rtopy>
    </pbndbox>
  </object>
</annotation>
