<annotation verified="yes">
  <folder>image</folder>
  <filename>2492</filename>
  <path>/home/cd/huawei-ssd/hwdata/image/2492.jpg</path>
  <source>
    <database>Unknown</database>
  </source>
  <size>
    <width>600</width>
    <height>600</height>
    <depth>1</depth>
  </size>
  <segmented>0</segmented>
  <object>
    <name>dianyuan</name>
    <pose>Unspecified</pose>
    <truncated>0</truncated>
    <difficult>0</difficult>
    <pbndbox>
      <ltopx>467</ltopx>
      <ltopy>134</ltopy>
      <lbottomx>480</lbottomx>
      <lbottomy>16</lbottomy>
      <rbottomx>412</rbottomx>
      <rbottomy>1</rbottomy>
      <rtopx>402</rtopx>
      <rtopy>117</rtopy>
    </pbndbox>
  </object>
  <object>
    <name>guangkou</name>
    <pose>Unspecified</pose>
    <truncated>0</truncated>
    <difficult>0</difficult>
    <pbndbox>
      <ltopx>426</ltopx>
      <ltopy>310</ltopy>
      <lbottomx>433</lbottomx>
      <lbottomy>278</lbottomy>
      <rbottomx>403</rbottomx>
      <rbottomy>273</rbottomy>
      <rtopx>398</rtopx>
      <rtopy>306</rtopy>
    </pbndbox>
  </object>
  <object>
    <name>guangkou</name>
    <pose>Unspecified</pose>
    <truncated>0</truncated>
    <difficult>0</difficult>
    <pbndbox>
      <ltopx>412</ltopx>
      <ltopy>440</ltopy>
      <lbottomx>423</lbottomx>
      <lbottomy>402</lbottomy>
      <rbottomx>393</rbottomx>
      <rbottomy>397</rbottomy>
      <rtopx>385</rtopx>
      <rtopy>434</rtopy>
    </pbndbox>
  </object>
</annotation>
