<annotation verified="no">
  <folder>image</folder>
  <filename>1367</filename>
  <path>/home/cd/huawei-ssd/hwdata/image/1367.jpg</path>
  <source>
    <database>Unknown</database>
  </source>
  <size>
    <width>600</width>
    <height>600</height>
    <depth>1</depth>
  </size>
  <segmented>0</segmented>
  <object>
    <name>guangkou</name>
    <pose>Unspecified</pose>
    <truncated>0</truncated>
    <difficult>0</difficult>
    <pbndbox>
      <ltopx>431</ltopx>
      <ltopy>174</ltopy>
      <lbottomx>404</lbottomx>
      <lbottomy>209</lbottomy>
      <rbottomx>426</rbottomx>
      <rbottomy>226</rbottomy>
      <rtopx>452</rtopx>
      <rtopy>192</rtopy>
    </pbndbox>
  </object>
  <object>
    <name>guangkou</name>
    <pose>Unspecified</pose>
    <truncated>0</truncated>
    <difficult>0</difficult>
    <pbndbox>
      <ltopx>498</ltopx>
      <ltopy>90</ltopy>
      <lbottomx>470</lbottomx>
      <lbottomy>124</lbottomy>
      <rbottomx>492</rbottomx>
      <rbottomy>141</rbottomy>
      <rtopx>521</rtopx>
      <rtopy>108</rtopy>
    </pbndbox>
  </object>
</annotation>
