<annotation verified="no">
  <folder>image</folder>
  <filename>1590</filename>
  <path>/home/cd/huawei-ssd/hwdata/image/1590.jpg</path>
  <source>
    <database>Unknown</database>
  </source>
  <size>
    <width>600</width>
    <height>600</height>
    <depth>1</depth>
  </size>
  <segmented>0</segmented>
  <object>
    <name>dianyuan</name>
    <pose>Unspecified</pose>
    <truncated>0</truncated>
    <difficult>0</difficult>
    <pbndbox>
      <ltopx>240</ltopx>
      <ltopy>285</ltopy>
      <lbottomx>335</lbottomx>
      <lbottomy>206</lbottomy>
      <rbottomx>306</rbottomx>
      <rbottomy>159</rbottomy>
      <rtopx>209</rtopx>
      <rtopy>239</rtopy>
    </pbndbox>
  </object>
  <object>
    <name>guangkou</name>
    <pose>Unspecified</pose>
    <truncated>0</truncated>
    <difficult>0</difficult>
    <pbndbox>
      <ltopx>58</ltopx>
      <ltopy>388</ltopy>
      <lbottomx>86</lbottomx>
      <lbottomy>373</lbottomy>
      <rbottomx>70</rbottomx>
      <rbottomy>353</rbottomy>
      <rtopx>44</rtopx>
      <rtopy>368</rtopy>
    </pbndbox>
  </object>
</annotation>
