<annotation verified="no">
  <folder>image</folder>
  <filename>2169</filename>
  <path>/home/cd/huawei-ssd/hwdata/image/2169.jpg</path>
  <source>
    <database>Unknown</database>
  </source>
  <size>
    <width>600</width>
    <height>600</height>
    <depth>1</depth>
  </size>
  <segmented>0</segmented>
  <object>
    <name>dianyuan</name>
    <pose>Unspecified</pose>
    <truncated>0</truncated>
    <difficult>0</difficult>
    <pbndbox>
      <ltopx>173</ltopx>
      <ltopy>113</ltopy>
      <lbottomx>217</lbottomx>
      <lbottomy>204</lbottomy>
      <rbottomx>277</rbottomx>
      <rbottomy>191</rbottomy>
      <rtopx>231</rtopx>
      <rtopy>98</rtopy>
    </pbndbox>
  </object>
</annotation>
