<annotation verified="yes">
  <folder>image</folder>
  <filename>2584</filename>
  <path>/home/cd/huawei-ssd/hwdata/image/2584.jpg</path>
  <source>
    <database>Unknown</database>
  </source>
  <size>
    <width>600</width>
    <height>600</height>
    <depth>1</depth>
  </size>
  <segmented>0</segmented>
  <object>
    <name>dianyuan</name>
    <pose>Unspecified</pose>
    <truncated>0</truncated>
    <difficult>0</difficult>
    <pbndbox>
      <ltopx>132</ltopx>
      <ltopy>339</ltopy>
      <lbottomx>222</lbottomx>
      <lbottomy>230</lbottomy>
      <rbottomx>170</rbottomx>
      <rbottomy>184</rbottomy>
      <rtopx>78</rtopx>
      <rtopy>291</rtopy>
    </pbndbox>
  </object>
</annotation>
